cylearn/__init__.py
cylearn/Data/Dataset.py
cylearn/Data/Loader.py
cylearn/Data/__init__.py
cylearn-0.1.4.dist-info/LICENSE
cylearn-0.1.4.dist-info/METADATA
cylearn-0.1.4.dist-info/WHEEL
cylearn-0.1.4.dist-info/top_level.txt
cylearn-0.1.4.dist-info/RECORD
