Metadata-Version: 2.1
Name: cylearn
Version: 0.1.4
Summary: A collection of tools for machine learning.
Home-page: https://github.com/ADNRs/cylearn
Author: Chung-Yi Chen (ADNRs)
License: UNKNOWN
Platform: UNKNOWN
Classifier: Development Status :: 1 - Planning
Classifier: License :: OSI Approved :: GNU General Public License v3 (GPLv3)
Classifier: Operating System :: OS Independent
Classifier: Programming Language :: Python :: 3
Requires-Python: >=3.6
License-File: LICENSE
